surrosdk.py
surrosdk-0.0.1a1.dist-info/WHEEL
surrosdk-0.0.1a1.dist-info/METADATA
surrosdk-0.0.1a1.dist-info/RECORD
